inkcollector/__init__.py
inkcollector/cli.py
inkcollector/lorcast.py
inkcollector-1.0.0.dist-info/METADATA
inkcollector-1.0.0.dist-info/WHEEL
inkcollector-1.0.0.dist-info/entry_points.txt
inkcollector-1.0.0.dist-info/RECORD
