Metadata-Version: 2.4
Name: inkcollector
Version: 1.0.0
Summary: Inkcollector is a CLI tool for collecting data about the disney lorcana trading card game.
Project-URL: Homepage, https://bertcafecito.github.io/inkcollector/
Project-URL: Documentation, https://bertcafecito.github.io/inkcollector/
Project-URL: Repository, https://github.com/bertcafecito/inkcollector
Project-URL: Bug Tracker, https://github.com/bertcafecito/inkcollector/issues
Project-URL: Changelog, https://github.com/bertcafecito/inkcollector/blob/main/CHANGELOG.md
Author-email: Bert Cafecito <your-email@example.com>
License-Expression: MIT
Keywords: disney,lorcana
Classifier: Development Status :: 3 - Alpha
Classifier: Environment :: Console
Classifier: Intended Audience :: Developers
Classifier: License :: OSI Approved :: MIT License
Classifier: Operating System :: OS Independent
Classifier: Programming Language :: Python :: 3
Classifier: Programming Language :: Python :: 3.9
Classifier: Programming Language :: Python :: 3.10
Classifier: Programming Language :: Python :: 3.11
Classifier: Programming Language :: Python :: 3.12
Requires-Python: >=3.9
Requires-Dist: requests>=2.32.3
Provides-Extra: dev
Requires-Dist: black>=23.0.0; extra == 'dev'
Requires-Dist: flake8>=6.0.0; extra == 'dev'
Requires-Dist: isort>=5.12.0; extra == 'dev'
Requires-Dist: pytest-cov>=4.0.0; extra == 'dev'
Requires-Dist: pytest-mock>=3.10.0; extra == 'dev'
Requires-Dist: pytest>=7.0.0; extra == 'dev'
Provides-Extra: docs
Requires-Dist: sphinx-rtd-theme>=3.0.2; extra == 'docs'
Requires-Dist: sphinx>=8.2.3; extra == 'docs'
